llmcc-0.2.18.dist-info/METADATA
llmcc-0.2.18.dist-info/WHEEL
llmcc_bindings/__init__.py
llmcc_bindings/llmcc_bindings.pyd
llmcc-0.2.18.dist-info/RECORD
