Metadata-Version: 2.4
Name: llmcc
Version: 0.2.18
Classifier: Development Status :: 3 - Alpha
Classifier: Intended Audience :: Developers
Classifier: License :: OSI Approved :: Apache Software License
Classifier: Operating System :: OS Independent
Classifier: Programming Language :: Python :: 3
Classifier: Programming Language :: Python :: 3.8
Classifier: Programming Language :: Python :: 3.9
Classifier: Programming Language :: Python :: 3.10
Classifier: Programming Language :: Python :: 3.11
Classifier: Programming Language :: Python :: 3.12
Classifier: Programming Language :: Rust
Classifier: Topic :: Software Development :: Libraries :: Python Modules
Requires-Dist: pytest>=7.0 ; extra == 'dev'
Requires-Dist: pytest-cov>=4.0 ; extra == 'dev'
Requires-Dist: black>=23.0 ; extra == 'dev'
Requires-Dist: ruff>=0.1.0 ; extra == 'dev'
Requires-Dist: mypy>=1.0 ; extra == 'dev'
Provides-Extra: dev
Summary: LLM Context Compiler - Universal context builder for any language and document type
Keywords: llm,compiler,context,code-analysis,rust
Home-Page: https://github.com/allenanswerzq/llmcc
Author: llmcc contributors
License: Apache-2.0
Requires-Python: >=3.8
Project-URL: Homepage, https://github.com/allenanswerzq/llmcc
Project-URL: Documentation, https://github.com/allenanswerzq/llmcc#readme
Project-URL: Repository, https://github.com/allenanswerzq/llmcc.git
Project-URL: Issues, https://github.com/allenanswerzq/llmcc/issues
